quantlite/__init__.py
quantlite/backtesting.py
quantlite/data_generation.py
quantlite/metrics.py
quantlite/monte_carlo.py
quantlite/visualisation.py
quantlite/instruments/__init__.py
quantlite/instruments/bond_pricing.py
quantlite/instruments/exotic_options.py
quantlite/instruments/option_pricing.py
QuantLite-0.1.0.dist-info/LICENSE
QuantLite-0.1.0.dist-info/METADATA
QuantLite-0.1.0.dist-info/WHEEL
QuantLite-0.1.0.dist-info/top_level.txt
QuantLite-0.1.0.dist-info/RECORD
