Metadata-Version: 2.1
Name: QuantLite
Version: 0.1.0
Summary: A robust quant finance library
Author-email: Prasant Sudhakaran <code@prasant.net>
License: MIT License
Keywords: quant,finance,monte carlo,exotic options
Requires-Python: >=3.8
License-File: LICENSE
Requires-Dist: numpy
Requires-Dist: pandas
Requires-Dist: scipy
Requires-Dist: matplotlib
Requires-Dist: mplfinance
